MANIFEST.in
README.md
dev.txt
setup.py
deceit/__init__.py
deceit/adapters.py
deceit/api_client.py
deceit/encoders.py
deceit/exceptions.py
deceit.egg-info/PKG-INFO
deceit.egg-info/SOURCES.txt
deceit.egg-info/dependency_links.txt
deceit.egg-info/requires.txt
deceit.egg-info/top_level.txt